iosresignapp/__init__.py
iosresignapp/codesign.py
iosresignapp/command.py
iosresignapp/resign.py
iosresignapp/security.py
iosresignapp/util.py
iOSReSignApp-1.5.8.dist-info/LICENSE
iOSReSignApp-1.5.8.dist-info/METADATA
iOSReSignApp-1.5.8.dist-info/WHEEL
iOSReSignApp-1.5.8.dist-info/entry_points.txt
iOSReSignApp-1.5.8.dist-info/top_level.txt
iOSReSignApp-1.5.8.dist-info/RECORD
