Metadata-Version: 2.1
Name: iOSReSignApp
Version: 1.5.8
Summary: UNKNOWN
Home-page: https://github.com/shede333/iOSReSignApp
Author: shede333
Author-email: 333wshw@163.com
License: UNKNOWN
Keywords: codesign ios resign re-sign re_sign re sign app
Platform: UNKNOWN
Classifier: Development Status :: 5 - Production/Stable
Classifier: Natural Language :: Chinese (Simplified)
Classifier: License :: OSI Approved :: MIT License
Classifier: Operating System :: MacOS :: MacOS X
Classifier: Operating System :: POSIX
Classifier: Topic :: Software Development :: Libraries :: Python Modules
Classifier: Programming Language :: Python
Classifier: Programming Language :: Python :: 3
Classifier: Programming Language :: Python :: 3.6
Classifier: Programming Language :: Python :: 3.7
Classifier: Programming Language :: Python :: 3.8
Requires-Python: ~=3.6
License-File: LICENSE
Requires-Dist: PyMobileProvision (~=1.3)
Requires-Dist: iOSAppInfoParser (~=1.0)
